racksdb/__init__.py
racksdb/bases.py
racksdb/errors.py
racksdb/exec.py
racksdb/version.py
racksdb/views.py
racksdb/drawers/__init__.py
racksdb/drawers/axonometric_infrastructure.py
racksdb/drawers/base.py
racksdb/drawers/infrastructure.py
racksdb/drawers/parameters.py
racksdb/drawers/room.py
racksdb/drawers/coordinates/__init__.py
racksdb/drawers/coordinates/base.py
racksdb/drawers/coordinates/json.py
racksdb/drawers/coordinates/yaml.py
racksdb/drawers/dtypes/__init__.py
racksdb/drawers/dtypes/hexcolor.py
racksdb/dtypes/__init__.py
racksdb/dtypes/angle.py
racksdb/dtypes/bits.py
racksdb/dtypes/bytes.py
racksdb/dtypes/dimension.py
racksdb/dtypes/netif_type.py
racksdb/dtypes/rack_height.py
racksdb/dtypes/rack_width.py
racksdb/dtypes/storage_type.py
racksdb/dtypes/watts.py
racksdb/generic/__init__.py
racksdb/generic/db.py
racksdb/generic/definedtype.py
racksdb/generic/errors.py
racksdb/generic/openapi.py
racksdb/generic/schema.py
racksdb/generic/views.py
racksdb/generic/dumpers/__init__.py
racksdb/generic/dumpers/_common.py
racksdb/generic/dumpers/console.py
racksdb/generic/dumpers/json.py
racksdb/generic/dumpers/yaml.py
racksdb/tests/__init__.py
racksdb/tests/test_defined_type_hexcolor.py
racksdb/tests/test_defined_type_watts.py
racksdb/tests/test_exec.py
racksdb/tests/test_racksdb.py
racksdb/tests/drawers/__init__.py
racksdb/tests/drawers/test_axonometric_infrastructure.py
racksdb/tests/drawers/test_base.py
racksdb/tests/drawers/test_infrastructure.py
racksdb/tests/drawers/test_parameters.py
racksdb/tests/generic/__init__.py
racksdb/tests/generic/test_db.py
racksdb/tests/generic/test_db_dict.py
racksdb/tests/generic/test_db_list.py
racksdb/tests/generic/test_db_loader.py
racksdb/tests/generic/test_openapi.py
racksdb/tests/generic/test_schema.py
racksdb/tests/generic/test_schema_defined_type_loader.py
racksdb/tests/generic/test_schema_file_loader.py
racksdb/tests/generic/test_views.py
racksdb/tests/generic/dumpers/__init__.py
racksdb-0.6.0.dist-info/licenses/LICENSE
racksdb-0.6.0.dist-info/METADATA
racksdb-0.6.0.dist-info/WHEEL
racksdb-0.6.0.dist-info/entry_points.txt
racksdb-0.6.0.dist-info/top_level.txt
racksdb-0.6.0.dist-info/RECORD
