Metadata-Version: 2.4
Name: RacksDB
Version: 0.6.0
Summary: Modelize your datacenters infrastructures in YAML database
Author-email: Rémi Palancher <remi@rackslab.io>
License: MIT
Project-URL: Homepage, https://github.com/rackslab/RacksDB
Project-URL: Bug Tracker, https://github.com/rackslab/RacksDB/issues
Keywords: cmdb,inventory,yaml,datacenters,racks,hpc,cluster
Classifier: Development Status :: 5 - Production/Stable
Classifier: Environment :: Console
Classifier: Intended Audience :: System Administrators
Classifier: Topic :: Software Development :: Libraries :: Python Modules
Classifier: Topic :: Database :: Database Engines/Servers
Classifier: Topic :: System :: Clustering
Classifier: Topic :: System :: Systems Administration
Requires-Python: >=3.6
License-File: LICENSE
Requires-Dist: PyYAML
Requires-Dist: ClusterShell
Requires-Dist: pycairo
Requires-Dist: PyGObject
Requires-Dist: RFL.log>=1.6.0
Provides-Extra: dev
Requires-Dist: Flask-Cors; extra == "dev"
Provides-Extra: web
Requires-Dist: Flask; extra == "web"
Requires-Dist: requests-toolbelt; extra == "web"
Provides-Extra: tests
Requires-Dist: coverage; extra == "tests"
Requires-Dist: parameterized; extra == "tests"
Requires-Dist: pytest; extra == "tests"
Requires-Dist: pytest-cov; extra == "tests"
Dynamic: license-file
